<?xml version="1.0"?>
<!--<!DOCTYPE metadata SYSTEM "http://www.esri.com/metadata/esriprof80.dtd">-->
<metadata xml:lang="nl"><Esri><CreaDate>20120306</CreaDate><CreaTime>16064300</CreaTime><SyncOnce>FALSE</SyncOnce><SyncDate>20111128</SyncDate><SyncTime>15563700</SyncTime><ModDate>20111128</ModDate><ModTime>15563700</ModTime><DataProperties><lineage><Process ToolSource="C:\Program Files\ArcGIS\ArcToolbox\Toolboxes\Data Management Tools.tbx\Merge" Date="20111128" Time="155637">Merge HCs_Kirehe_included;HCs_Kibungo;All_included_HCs D:\test\HCs_Kirehe_sets.gdb\HCs_Kirehe_included_Merge "FOSAID 'FOSAID' true true false 8 Double 0 0 ,First,#,HCs_Kirehe_included,FOSAID,-1,-1,HCs_Kibungo,FOSAID,-1,-1,All_included_HCs,FOSAID,-1,-1;GovtFOSACo 'GovtFOSACo' true true false 10 Text 0 0 ,First,#,HCs_Kirehe_included,GovtFOSACo,-1,-1,HCs_Kibungo,GovtFOSACo,-1,-1,All_included_HCs,GovtFOSACo,-1,-1;FOSAName 'FOSAName' true true false 75 Text 0 0 ,First,#,HCs_Kirehe_included,FOSAName,-1,-1,HCs_Kibungo,FOSAName,-1,-1,All_included_HCs,FOSAName,-1,-1;TypeFOSAab 'TypeFOSAab' true true false 7 Text 0 0 ,First,#,HCs_Kirehe_included,TypeFOSAab,-1,-1,HCs_Kibungo,TypeFOSAab,-1,-1,All_included_HCs,TypeFOSAab,-1,-1;ProvinceCo 'ProvinceCo' true true false 2 Text 0 0 ,First,#,HCs_Kirehe_included,ProvinceCo,-1,-1,HCs_Kibungo,ProvinceCo,-1,-1,All_included_HCs,ProvinceCo,-1,-1;ProvCode 'ProvCode' true true false 2 Text 0 0 ,First,#,HCs_Kirehe_included,ProvCode,-1,-1,HCs_Kibungo,ProvCode,-1,-1,All_included_HCs,ProvCode,-1,-1;ProvinceNa 'ProvinceNa' true true false 40 Text 0 0 ,First,#,HCs_Kirehe_included,ProvinceNa,-1,-1,HCs_Kibungo,ProvinceNa,-1,-1,All_included_HCs,ProvinceNa,-1,-1;DistrictCo 'DistrictCo' true true false 4 Text 0 0 ,First,#,HCs_Kirehe_included,DistrictCo,-1,-1,HCs_Kibungo,DistrictCo,-1,-1,All_included_HCs,DistrictCo,-1,-1;DistrictNa 'DistrictNa' true true false 40 Text 0 0 ,First,#,HCs_Kirehe_included,DistrictNa,-1,-1,HCs_Kibungo,DistrictNa,-1,-1,All_included_HCs,DistrictNa,-1,-1;SectorCode 'SectorCode' true true false 10 Text 0 0 ,First,#,HCs_Kirehe_included,SectorCode,-1,-1,HCs_Kibungo,SectorCode,-1,-1,All_included_HCs,SectorCode,-1,-1;SectorName 'SectorName' true true false 75 Text 0 0 ,First,#,HCs_Kirehe_included,SectorName,-1,-1,HCs_Kibungo,SectorName,-1,-1,All_included_HCs,SectorName,-1,-1;LatitudeDe 'LatitudeDe' true true false 8 Double 0 0 ,First,#,HCs_Kirehe_included,LatitudeDe,-1,-1,HCs_Kibungo,LatitudeDe,-1,-1,All_included_HCs,LatitudeDe,-1,-1;LongitudeD 'LongitudeD' true true false 8 Double 0 0 ,First,#,HCs_Kirehe_included,LongitudeD,-1,-1,HCs_Kibungo,LongitudeD,-1,-1,All_included_HCs,LongitudeD,-1,-1;PrivatePub 'PrivatePub' true true false 100 Text 0 0 ,First,#,HCs_Kirehe_included,PrivatePub,-1,-1,HCs_Kibungo,PrivatePub,-1,-1,All_included_HCs,PrivatePub,-1,-1;Population 'Population' true true false 8 Double 0 0 ,First,#,HCs_Kirehe_included,Population,-1,-1,HCs_Kibungo,Population,-1,-1,All_included_HCs,Population,-1,-1;Populati_1 'Populati_1' true true false 8 Double 0 0 ,First,#,HCs_Kirehe_included,Populati_1,-1,-1,HCs_Kibungo,Populati_1,-1,-1,All_included_HCs,Populati_1,-1,-1;Populati_2 'Populati_2' true true false 254 Text 0 0 ,First,#,HCs_Kirehe_included,Populati_2,-1,-1,HCs_Kibungo,Populati_2,-1,-1,All_included_HCs,Populati_2,-1,-1;CFCode 'CFCode' true true false 8 Double 0 0 ,First,#,HCs_Kirehe_included,CFCode,-1,-1,HCs_Kibungo,CFCode,-1,-1,All_included_HCs,CFCode,-1,-1;ParentFOSA 'ParentFOSA' true true false 75 Text 0 0 ,First,#,HCs_Kirehe_included,ParentFOSA,-1,-1,HCs_Kibungo,ParentFOSA,-1,-1,All_included_HCs,ParentFOSA,-1,-1;FOSANameTy 'FOSANameTy' true true false 254 Text 0 0 ,First,#,HCs_Kirehe_included,FOSANameTy,-1,-1,HCs_Kibungo,FOSANameTy,-1,-1,All_included_HCs,FOSANameTy,-1,-1;PBF_phase 'PBF_phase' true true false 2 Short 0 0 ,First,#,HCs_Kirehe_included,PBF_phase,-1,-1,HCs_Kibungo,PBF_phase,-1,-1,All_included_HCs,PBF_phase,-1,-1"</Process><Process ToolSource="C:\Program Files\ArcGIS\Desktop10.0\ArcToolbox\Toolboxes\Analysis Tools.tbx\Near" Date="20120308" Time="101219">Near HealthCenters main_roads # NO_LOCATION NO_ANGLE</Process></lineage></DataProperties><MetaID>{03C48D67-DB43-4883-8BE3-C0CC764FB753}</MetaID></Esri><idinfo><native Sync="TRUE">Microsoft Windows Vista Version 6.1 (Build 7600) ; ESRI ArcCatalog 9.3.1.3000</native><descript><langdata Sync="TRUE">nl</langdata><abstract>REQUIRED: A brief narrative summary of the data set.</abstract><purpose>REQUIRED: A summary of the intentions with which the data set was developed.</purpose></descript><citation><citeinfo><origin>REQUIRED: The name of an organization or individual that developed the data set.</origin><pubdate>REQUIRED: The date when the data set is published or otherwise made available for release.</pubdate><title Sync="TRUE">HCs_Kirehe_included_Merge</title><ftname Sync="TRUE">HCs_Kirehe_included_Merge</ftname><geoform Sync="TRUE">vector digital data</geoform><onlink Sync="TRUE"></onlink></citeinfo></citation><timeperd><current>REQUIRED: The basis on which the time period of content information is determined.</current><timeinfo><sngdate><caldate>REQUIRED: The year (and optionally month, or month and day) for which the data set corresponds to the ground.</caldate></sngdate></timeinfo></timeperd><status><progress>REQUIRED: The state of the data set.</progress><update>REQUIRED: The frequency with which changes and additions are made to the data set after the initial data set is completed.</update></status><spdom><bounding><westbc Sync="TRUE">REQUIRED: Western-most coordinate of the limit of coverage expressed in longitude.</westbc><eastbc Sync="TRUE">REQUIRED: Eastern-most coordinate of the limit of coverage expressed in longitude.</eastbc><northbc Sync="TRUE">REQUIRED: Northern-most coordinate of the limit of coverage expressed in latitude.</northbc><southbc Sync="TRUE">REQUIRED: Southern-most coordinate of the limit of coverage expressed in latitude.</southbc></bounding></spdom><keywords><theme><themekt>REQUIRED: Reference to a formally registered thesaurus or a similar authoritative source of theme keywords.</themekt><themekey>REQUIRED: Common-use word or phrase used to describe the subject of the data set.</themekey></theme></keywords><accconst>REQUIRED: Restrictions and legal prerequisites for accessing the data set.</accconst><useconst>REQUIRED: Restrictions and legal prerequisites for using the data set after access is granted.</useconst><natvform Sync="TRUE">File Geodatabase Feature Class</natvform></idinfo><dataIdInfo><envirDesc Sync="TRUE">Microsoft Windows Vista Version 6.1 (Build 7600) ; ESRI ArcCatalog 9.3.1.3000</envirDesc><dataLang><languageCode Sync="TRUE" value="nl"></languageCode></dataLang><idCitation><resTitle Sync="TRUE">HCs_Kirehe_included_Merge</resTitle></idCitation></dataIdInfo><metainfo><langmeta Sync="TRUE">nl</langmeta><metstdn Sync="TRUE">FGDC Content Standards for Digital Geospatial Metadata</metstdn><metstdv Sync="TRUE">FGDC-STD-001-1998</metstdv><mettc Sync="TRUE">local time</mettc><metextns><onlink Sync="TRUE">http://www.esri.com/metadata/esriprof80.html</onlink><metprof Sync="TRUE">ESRI Metadata Profile</metprof></metextns><metc><cntinfo><cntorgp><cntper>REQUIRED: The person responsible for the metadata information.</cntper><cntorg>REQUIRED: The organization responsible for the metadata information.</cntorg></cntorgp><cntaddr><addrtype>REQUIRED: The mailing and/or physical address for the organization or individual.</addrtype><city>REQUIRED: The city of the address.</city><state>REQUIRED: The state or province of the address.</state><postal>REQUIRED: The ZIP or other postal code of the address.</postal></cntaddr><cntvoice>REQUIRED: The telephone number by which individuals can speak to the organization or individual.</cntvoice></cntinfo></metc><metd Sync="TRUE">20111128</metd></metainfo><mdLang><languageCode Sync="TRUE" value="nl"></languageCode></mdLang><mdStanName Sync="TRUE">ISO 19115 Geographic Information - Metadata</mdStanName><mdStanVer Sync="TRUE">DIS_ESRI1.0</mdStanVer><mdChar><CharSetCd Sync="TRUE" value="004"></CharSetCd></mdChar><mdHrLv><ScopeCd Sync="TRUE" value="005"></ScopeCd></mdHrLv><mdHrLvName Sync="TRUE">dataset</mdHrLvName><distinfo><resdesc Sync="TRUE">Downloadable Data</resdesc></distinfo><distInfo><distributor><distorTran><onLineSrc><orDesc Sync="TRUE">002</orDesc><linkage Sync="TRUE">file://</linkage><protocol Sync="TRUE">Local Area Network</protocol></onLineSrc></distorTran><distorFormat><formatName Sync="TRUE">File Geodatabase Feature Class</formatName></distorFormat></distributor></distInfo><spdoinfo><direct Sync="TRUE">Vector</direct><ptvctinf><esriterm Name="HCs_Kirehe_included_Merge"><efeatyp Sync="TRUE">Simple</efeatyp><efeageom Sync="TRUE">Point</efeageom><esritopo Sync="TRUE">FALSE</esritopo><efeacnt Sync="TRUE">0</efeacnt><spindex Sync="TRUE">TRUE</spindex><linrefer Sync="TRUE">FALSE</linrefer></esriterm><sdtsterm Name="HCs_Kirehe_included_Merge"><sdtstype Sync="TRUE">Entity point</sdtstype><ptvctcnt Sync="TRUE">0</ptvctcnt></sdtsterm></ptvctinf></spdoinfo><spref><horizsys><cordsysn><geogcsn Sync="TRUE">GCS_Arc_1960</geogcsn><projcsn Sync="TRUE">Transverse Mercator</projcsn></cordsysn><planar><mapproj><mapprojn Sync="TRUE">Transverse Mercator</mapprojn><transmer><sfctrmer Sync="TRUE">0.999900</sfctrmer><longcm Sync="TRUE">30.000000</longcm><latprjo Sync="TRUE">0.000000</latprjo><feast Sync="TRUE">500000.000000</feast><fnorth Sync="TRUE">10000000.000000</fnorth></transmer></mapproj><planci><plance Sync="TRUE">coordinate pair</plance><plandu Sync="TRUE">meters</plandu><coordrep><absres Sync="TRUE">0.000000</absres><ordres Sync="TRUE">0.000000</ordres></coordrep></planci></planar><geodetic><horizdn Sync="TRUE">D_Arc_1960</horizdn><ellips Sync="TRUE">Clarke_1880_RGS</ellips><semiaxis Sync="TRUE">6378249.145000</semiaxis><denflat Sync="TRUE">293.465000</denflat></geodetic></horizsys></spref><refSysInfo><RefSystem><refSysID><identCode Sync="TRUE">Transverse Mercator</identCode></refSysID></RefSystem></refSysInfo><spatRepInfo><VectSpatRep><topLvl><TopoLevCd Sync="TRUE" value="001"></TopoLevCd></topLvl><geometObjs Name="HCs_Kirehe_included_Merge"><geoObjTyp><GeoObjTypCd Sync="TRUE" value="004"></GeoObjTypCd></geoObjTyp><geoObjCnt Sync="TRUE">0</geoObjCnt></geometObjs></VectSpatRep></spatRepInfo><eainfo><detailed Name="HCs_Kirehe_included_Merge"><enttyp><enttypl Sync="TRUE">HCs_Kirehe_included_Merge</enttypl><enttypt Sync="TRUE">Feature Class</enttypt><enttypc Sync="TRUE">0</enttypc></enttyp><attr><attrlabl Sync="TRUE">OBJECTID</attrlabl><attalias Sync="TRUE">OBJECTID</attalias><attrtype Sync="TRUE">OID</attrtype><attwidth Sync="TRUE">4</attwidth><atprecis Sync="TRUE">0</atprecis><attscale Sync="TRUE">0</attscale><attrdef Sync="TRUE">Internal feature number.</attrdef><attrdefs Sync="TRUE">ESRI</attrdefs><attrdomv><udom Sync="TRUE">Sequential unique whole numbers that are automatically generated.</udom></attrdomv></attr><attr><attrlabl Sync="TRUE">Shape</attrlabl><attalias Sync="TRUE">Shape</attalias><attrtype Sync="TRUE">Geometry</attrtype><attwidth Sync="TRUE">0</attwidth><atprecis Sync="TRUE">0</atprecis><attscale Sync="TRUE">0</attscale><attrdef Sync="TRUE">Feature geometry.</attrdef><attrdefs Sync="TRUE">ESRI</attrdefs><attrdomv><udom Sync="TRUE">Coordinates defining the features.</udom></attrdomv></attr><attr><attrlabl Sync="TRUE">FOSAID</attrlabl><attalias Sync="TRUE">FOSAID</attalias><attrtype Sync="TRUE">Double</attrtype><attwidth Sync="TRUE">8</attwidth><atprecis Sync="TRUE">0</atprecis><attscale Sync="TRUE">0</attscale></attr><attr><attrlabl Sync="TRUE">GovtFOSACo</attrlabl><attalias Sync="TRUE">GovtFOSACo</attalias><attrtype Sync="TRUE">String</attrtype><attwidth Sync="TRUE">10</attwidth><atprecis Sync="TRUE">0</atprecis><attscale Sync="TRUE">0</attscale></attr><attr><attrlabl Sync="TRUE">FOSAName</attrlabl><attalias Sync="TRUE">FOSAName</attalias><attrtype Sync="TRUE">String</attrtype><attwidth Sync="TRUE">75</attwidth><atprecis Sync="TRUE">0</atprecis><attscale Sync="TRUE">0</attscale></attr><attr><attrlabl Sync="TRUE">TypeFOSAab</attrlabl><attalias Sync="TRUE">TypeFOSAab</attalias><attrtype Sync="TRUE">String</attrtype><attwidth Sync="TRUE">7</attwidth><atprecis Sync="TRUE">0</atprecis><attscale Sync="TRUE">0</attscale></attr><attr><attrlabl Sync="TRUE">ProvinceCo</attrlabl><attalias Sync="TRUE">ProvinceCo</attalias><attrtype Sync="TRUE">String</attrtype><attwidth Sync="TRUE">2</attwidth><atprecis Sync="TRUE">0</atprecis><attscale Sync="TRUE">0</attscale></attr><attr><attrlabl Sync="TRUE">ProvCode</attrlabl><attalias Sync="TRUE">ProvCode</attalias><attrtype Sync="TRUE">String</attrtype><attwidth Sync="TRUE">2</attwidth><atprecis Sync="TRUE">0</atprecis><attscale Sync="TRUE">0</attscale></attr><attr><attrlabl Sync="TRUE">ProvinceNa</attrlabl><attalias Sync="TRUE">ProvinceNa</attalias><attrtype Sync="TRUE">String</attrtype><attwidth Sync="TRUE">40</attwidth><atprecis Sync="TRUE">0</atprecis><attscale Sync="TRUE">0</attscale></attr><attr><attrlabl Sync="TRUE">DistrictCo</attrlabl><attalias Sync="TRUE">DistrictCo</attalias><attrtype Sync="TRUE">String</attrtype><attwidth Sync="TRUE">4</attwidth><atprecis Sync="TRUE">0</atprecis><attscale Sync="TRUE">0</attscale></attr><attr><attrlabl Sync="TRUE">DistrictNa</attrlabl><attalias Sync="TRUE">DistrictNa</attalias><attrtype Sync="TRUE">String</attrtype><attwidth Sync="TRUE">40</attwidth><atprecis Sync="TRUE">0</atprecis><attscale Sync="TRUE">0</attscale></attr><attr><attrlabl Sync="TRUE">SectorCode</attrlabl><attalias Sync="TRUE">SectorCode</attalias><attrtype Sync="TRUE">String</attrtype><attwidth Sync="TRUE">10</attwidth><atprecis Sync="TRUE">0</atprecis><attscale Sync="TRUE">0</attscale></attr><attr><attrlabl Sync="TRUE">SectorName</attrlabl><attalias Sync="TRUE">SectorName</attalias><attrtype Sync="TRUE">String</attrtype><attwidth Sync="TRUE">75</attwidth><atprecis Sync="TRUE">0</atprecis><attscale Sync="TRUE">0</attscale></attr><attr><attrlabl Sync="TRUE">LatitudeDe</attrlabl><attalias Sync="TRUE">LatitudeDe</attalias><attrtype Sync="TRUE">Double</attrtype><attwidth Sync="TRUE">8</attwidth><atprecis Sync="TRUE">0</atprecis><attscale Sync="TRUE">0</attscale></attr><attr><attrlabl Sync="TRUE">LongitudeD</attrlabl><attalias Sync="TRUE">LongitudeD</attalias><attrtype Sync="TRUE">Double</attrtype><attwidth Sync="TRUE">8</attwidth><atprecis Sync="TRUE">0</atprecis><attscale Sync="TRUE">0</attscale></attr><attr><attrlabl Sync="TRUE">PrivatePub</attrlabl><attalias Sync="TRUE">PrivatePub</attalias><attrtype Sync="TRUE">String</attrtype><attwidth Sync="TRUE">100</attwidth><atprecis Sync="TRUE">0</atprecis><attscale Sync="TRUE">0</attscale></attr><attr><attrlabl Sync="TRUE">Population</attrlabl><attalias Sync="TRUE">Population</attalias><attrtype Sync="TRUE">Double</attrtype><attwidth Sync="TRUE">8</attwidth><atprecis Sync="TRUE">0</atprecis><attscale Sync="TRUE">0</attscale></attr><attr><attrlabl Sync="TRUE">Populati_1</attrlabl><attalias Sync="TRUE">Populati_1</attalias><attrtype Sync="TRUE">Double</attrtype><attwidth Sync="TRUE">8</attwidth><atprecis Sync="TRUE">0</atprecis><attscale Sync="TRUE">0</attscale></attr><attr><attrlabl Sync="TRUE">Populati_2</attrlabl><attalias Sync="TRUE">Populati_2</attalias><attrtype Sync="TRUE">String</attrtype><attwidth Sync="TRUE">254</attwidth><atprecis Sync="TRUE">0</atprecis><attscale Sync="TRUE">0</attscale></attr><attr><attrlabl Sync="TRUE">CFCode</attrlabl><attalias Sync="TRUE">CFCode</attalias><attrtype Sync="TRUE">Double</attrtype><attwidth Sync="TRUE">8</attwidth><atprecis Sync="TRUE">0</atprecis><attscale Sync="TRUE">0</attscale></attr><attr><attrlabl Sync="TRUE">ParentFOSA</attrlabl><attalias Sync="TRUE">ParentFOSA</attalias><attrtype Sync="TRUE">String</attrtype><attwidth Sync="TRUE">75</attwidth><atprecis Sync="TRUE">0</atprecis><attscale Sync="TRUE">0</attscale></attr><attr><attrlabl Sync="TRUE">FOSANameTy</attrlabl><attalias Sync="TRUE">FOSANameTy</attalias><attrtype Sync="TRUE">String</attrtype><attwidth Sync="TRUE">254</attwidth><atprecis Sync="TRUE">0</atprecis><attscale Sync="TRUE">0</attscale></attr><attr><attrlabl Sync="TRUE">PBF_phase</attrlabl><attalias Sync="TRUE">PBF_phase</attalias><attrtype Sync="TRUE">SmallInteger</attrtype><attwidth Sync="TRUE">2</attwidth><atprecis Sync="TRUE">0</atprecis><attscale Sync="TRUE">0</attscale></attr></detailed></eainfo><mdDateSt Sync="TRUE">20111128</mdDateSt><dataqual><lineage><procstep><procdesc Sync="TRUE">Dataset copied.</procdesc><srcused Sync="TRUE">\\WINDOWS-N8W4MCO\D$\test\HCs_Kirehe_sets.gdb</srcused><procdate Sync="TRUE">20120306</procdate><proctime Sync="TRUE">16064300</proctime></procstep></lineage></dataqual></metadata>
